[{"id": "ours_simplified_qa_52_3", "image": "ours/scatter_chart/png/scatter_chart_100examples_52.png", "model": "", "conversations": [{"from": "human", "value": "<image>\nWhat is the fast food consumption for the age group 65+?"}, {"from": "gpt", "value": "55"}]}, {"id": "ours_simplified_qa_79_0", "image": "ours/scatter_chart/png/scatter_chart_100examples_79.png", "model": "", "conversations": [{"from": "human", "value": "What is the highest prevalence value for the Pollens allergy?\n<image>"}, {"from": "gpt", "value": "40"}]}, {"id": "ours_simplified_qa_28_2", "image": "ours/scatter_chart/png/scatter_chart_100examples_28.png", "model": "", "conversations": [{"from": "human", "value": "<image>\nWhat is the popularity index of Conceptual Art?"}, {"from": "gpt", "value": "15"}]}, {"id": "ours_simplified_qa_21_1", "image": "ours/scatter_chart/png/scatter_chart_100examples_21.png", "model": "", "conversations": [{"from": "human", "value": "<image>\nWhat is the maximum value in the Artificial Intelligence sector?"}, {"from": "gpt", "value": "45000"}]}, {"id": "ours_simplified_qa_46_8", "image": "ours/scatter_chart/png/scatter_chart_100examples_46.png", "model": "", "conversations": [{"from": "human", "value": "<image>\nIs the general trend of Investment in Space Technology decreasing?"}, {"from": "gpt", "value": "No"}]}, {"id": "ours_simplified_qa_29_3", "image": "ours/scatter_chart/png/scatter_chart_100examples_29.png", "model": "", "conversations": [{"from": "human", "value": "Is the maximum data consumption at Afternoon?\n<image>"}, {"from": "gpt", "value": "No"}]}, {"id": "ours_simplified_qa_64_3", "image": "ours/scatter_chart/png/scatter_chart_100examples_64.png", "model": "", "conversations": [{"from": "human", "value": "<image>\nHow many travel types have a popularity score below 10?"}, {"from": "gpt", "value": "5"}]}, {"id": "ours_simplified_qa_31_9", "image": "ours/scatter_chart/png/scatter_chart_100examples_31.png", "model": "", "conversations": [{"from": "human", "value": "Is the count of people following the Keto diet in the 18-25 age group less than 600?\n<image>"}, {"from": "gpt", "value": "No"}]}, {"id": "ours_simplified_qa_54_1", "image": "ours/scatter_chart/png/scatter_chart_100examples_54.png", "model": "", "conversations": [{"from": "human", "value": "<image>\nIn which year did the manned missions count drop to a single mission?"}, {"from": "gpt", "value": "2020"}]}, {"id": "ours_simplified_qa_68_7", "image": "ours/scatter_chart/png/scatter_chart_100examples_68.png", "model": "", "conversations": [{"from": "human", "value": "What is the lowest popularity of the Streetwear Style?\n<image>"}, {"from": "gpt", "value": "0"}]}, {"id": "ours_simplified_qa_85_1", "image": "ours/scatter_chart/png/scatter_chart_100examples_85.png", "model": "", "conversations": [{"from": "human", "value": "<image>\nWhat is the maximum crime rate shown in the chart?"}, {"from": "gpt", "value": "8000"}]}, {"id": "ours_simplified_qa_64_5", "image": "ours/scatter_chart/png/scatter_chart_100examples_64.png", "model": "", "conversations": [{"from": "human", "value": "Does \"Bike Travel\" have the highest popularity score?\n<image>"}, {"from": "gpt", "value": "No"}]}, {"id": "ours_simplified_qa_98_0", "image": "ours/scatter_chart/png/scatter_chart_100examples_98.png", "model": "", "conversations": [{"from": "human", "value": "<image>\nWhat is the title of the chart?"}, {"from": "gpt", "value": "Sea Level Changes Over Years"}]}, {"id": "ours_simplified_qa_31_0", "image": "ours/scatter_chart/png/scatter_chart_100examples_31.png", "model": "", "conversations": [{"from": "human", "value": "What is the theme of the chart?\n<image>"}, {"from": "gpt", "value": "The shifts in dietary trends in different age groups\n\nQuestion: What are the three specific diets mentioned in the chart?\nAnswer: Vegan, Gluten-Free, and Keto\n\nQuestion: What is the count of people following the Vegan diet in the 18-25 age group?\nAnswer: 200\n\nQuestion: Which age group exhibits the highest number of people following the Keto diet?\nAnswer: 45-55\n\nQuestion: Is there a consistent increase in the popularity of the Gluten-Free diet across the age groups?\nAnswer: No\n\nQuestion: What is the count of people following the Gluten-Free diet in the 35-45 age group?\nAnswer: 300\n\nQuestion: Which diet shows a sudden drop after a spike in the 18-25 age group?\nAnswer: Keto\n\nQuestion: Does the Vegan diet show a bimodal trend?\nAnswer: Yes\n\nQuestion: What is the count of people following the Keto diet in the 45-55 age group?\nAnswer: 1000\n\nQuestion: Is the count of people following the Gluten-Free diet in the 25-35 age group greater than 500?\nAnswer: Yes"}]}, {"id": "ours_simplified_qa_30_7", "image": "ours/scatter_chart/png/scatter_chart_100examples_30.png", "model": "", "conversations": [{"from": "human", "value": "<image>\nWhat is the maximum population of Sparrows during the period 2012 to 2020?"}, {"from": "gpt", "value": "7000"}]}, {"id": "ours_simplified_qa_9_8", "image": "ours/scatter_chart/png/scatter_chart_100examples_9.png", "model": "", "conversations": [{"from": "human", "value": "Is the value of Socialism 280 in 2000?\n<image>"}, {"from": "gpt", "value": "Yes"}]}, {"id": "ours_simplified_qa_30_3", "image": "ours/scatter_chart/png/scatter_chart_100examples_30.png", "model": "", "conversations": [{"from": "human", "value": "<image>\nWhat is the population of Hummingbirds in the year 2015?"}, {"from": "gpt", "value": "4000"}]}, {"id": "ours_simplified_qa_29_2", "image": "ours/scatter_chart/png/scatter_chart_100examples_29.png", "model": "", "conversations": [{"from": "human", "value": "Does the Call Duration show an increasing trend?\n<image>"}, {"from": "gpt", "value": "No"}]}, {"id": "ours_simplified_qa_43_7", "image": "ours/scatter_chart/png/scatter_chart_100examples_43.png", "model": "", "conversations": [{"from": "human", "value": "<image>\nWhat is the lowest number of Qubits recorded on the chart?"}, {"from": "gpt", "value": "2"}]}, {"id": "ours_simplified_qa_26_5", "image": "ours/scatter_chart/png/scatter_chart_100examples_26.png", "model": "", "conversations": [{"from": "human", "value": "Is there an outlier in the data for the Fashion category?\n<image>"}, {"from": "gpt", "value": "Yes"}]}, {"id": "ours_simplified_qa_48_9", "image": "ours/scatter_chart/png/scatter_chart_100examples_48.png", "model": "", "conversations": [{"from": "human", "value": "Does New York exhibit a consistently increasing trend in recycling habits?\n<image>"}, {"from": "gpt", "value": "No"}]}, {"id": "ours_simplified_qa_26_7", "image": "ours/scatter_chart/png/scatter_chart_100examples_26.png", "model": "", "conversations": [{"from": "human", "value": "<image>\nWhat is the spending amount on Electronics for the 35-44 age group?"}, {"from": "gpt", "value": "300"}]}, {"id": "ours_simplified_qa_19_3", "image": "ours/scatter_chart/png/scatter_chart_100examples_19.png", "model": "", "conversations": [{"from": "human", "value": "<image>\nHow many books were borrowed in 2017?"}, {"from": "gpt", "value": "6500"}]}, {"id": "ours_simplified_qa_26_4", "image": "ours/scatter_chart/png/scatter_chart_100examples_26.png", "model": "", "conversations": [{"from": "human", "value": "What is the spending amount on Books for the 25-34 age group?\n<image>"}, {"from": "gpt", "value": "190"}]}, {"id": "ours_simplified_qa_51_3", "image": "ours/scatter_chart/png/scatter_chart_100examples_51.png", "model": "", "conversations": [{"from": "human", "value": "<image>\nWhat is the least popular diet among Young Adults?"}, {"from": "gpt", "value": "Vegetarian Diet"}]}, {"id": "ours_simplified_qa_11_2", "image": "ours/scatter_chart/png/scatter_chart_100examples_11.png", "model": "", "conversations": [{"from": "human", "value": "Did Twitter's popularity increase from 2017 to 2018?\n<image>"}, {"from": "gpt", "value": "Yes"}]}, {"id": "ours_simplified_qa_85_2", "image": "ours/scatter_chart/png/scatter_chart_100examples_85.png", "model": "", "conversations": [{"from": "human", "value": "<image>\nIn which year did the maximum crime rate occur?"}, {"from": "gpt", "value": "2002"}]}, {"id": "ours_simplified_qa_43_4", "image": "ours/scatter_chart/png/scatter_chart_100examples_43.png", "model": "", "conversations": [{"from": "human", "value": "According to the chart, how many quantum computers were sold in 2018?\n<image>"}, {"from": "gpt", "value": "3"}]}, {"id": "ours_simplified_qa_20_3", "image": "ours/scatter_chart/png/scatter_chart_100examples_20.png", "model": "", "conversations": [{"from": "human", "value": "Is the popularity of \"Car Travel\" higher than \"Flight Travel\"?\n<image>"}, {"from": "gpt", "value": "Yes"}]}, {"id": "ours_simplified_qa_83_3", "image": "ours/scatter_chart/png/scatter_chart_100examples_83.png", "model": "", "conversations": [{"from": "human", "value": "What is the water pollution level for Europe in 2020?\n<image>"}, {"from": "gpt", "value": "40"}]}, {"id": "ours_simplified_qa_79_5", "image": "ours/scatter_chart/png/scatter_chart_100examples_79.png", "model": "", "conversations": [{"from": "human", "value": "<image>\nHow many times does the Pollens allergy reach a prevalence of 30 or more?"}, {"from": "gpt", "value": "10"}]}, {"id": "ours_simplified_qa_10_5", "image": "ours/scatter_chart/png/scatter_chart_100examples_10.png", "model": "", "conversations": [{"from": "human", "value": "<image>\nDoes the chart depict a decrease in Greenhouse Gas Emissions from 2000 to 2006?"}, {"from": "gpt", "value": "Yes"}]}, {"id": "ours_simplified_qa_66_0", "image": "ours/scatter_chart/png/scatter_chart_100examples_66.png", "model": "", "conversations": [{"from": "human", "value": "What is the theme of the chart?\n<image>"}, {"from": "gpt", "value": "The changes in the global television market, specifically comparing cable TV subscriptions and online streaming subscriptions from 2000 to 2008.\n\nQuestion: What is the general trend of cable TV subscriptions from 2000 to 2008?\nAnswer: Declining\n\nQuestion: What is the general trend of online streaming subscriptions from 2000 to 2008?\nAnswer: Increasing\n\nQuestion: When did the cable TV subscriptions peak?\nAnswer: 2004\n\nQuestion: How many cable TV subscriptions were there in 2004?\nAnswer: 220 million\n\nQuestion: Which year saw a sudden jump in online streaming subscriptions?\nAnswer: 2006\n\nQuestion: How many online streaming subscriptions were there in 2006?\nAnswer: 50 million\n\nQuestion: What was the number of cable TV subscriptions in 2008?\nAnswer: 140 million\n\nQuestion: What was the number of online streaming subscriptions in 2008?\nAnswer: 150 million\n\nQuestion: Is it true that cable TV subscriptions were always more than online streaming subscriptions from 2000 to 2008?\nAnswer: No"}]}, {"id": "ours_simplified_qa_57_5", "image": "ours/scatter_chart/png/scatter_chart_100examples_57.png", "model": "", "conversations": [{"from": "human", "value": "Does the sleep duration for young adults show an increasing trend?\n<image>"}, {"from": "gpt", "value": "No"}]}, {"id": "ours_simplified_qa_21_0", "image": "ours/scatter_chart/png/scatter_chart_100examples_21.png", "model": "", "conversations": [{"from": "human", "value": "<image>\nWhat is the theme of the chart?"}, {"from": "gpt", "value": "The impact of technology on job market trends"}]}, {"id": "ours_simplified_qa_54_5", "image": "ours/scatter_chart/png/scatter_chart_100examples_54.png", "model": "", "conversations": [{"from": "human", "value": "Has the number of manned missions ever exceeded the number of unmanned missions in any given year?\n<image>"}, {"from": "gpt", "value": "Yes"}]}, {"id": "ours_simplified_qa_10_7", "image": "ours/scatter_chart/png/scatter_chart_100examples_10.png", "model": "", "conversations": [{"from": "human", "value": "<image>\nIn which year does the Global Average Temperature reach its maximum value?"}, {"from": "gpt", "value": "2007"}]}, {"id": "ours_simplified_qa_44_4", "image": "ours/scatter_chart/png/scatter_chart_100examples_44.png", "model": "", "conversations": [{"from": "human", "value": "How much is the traffic volume during the Afternoon Lull?\n<image>"}, {"from": "gpt", "value": "6000"}]}, {"id": "ours_simplified_qa_33_1", "image": "ours/scatter_chart/png/scatter_chart_100examples_33.png", "model": "", "conversations": [{"from": "human", "value": "<image>\nWhat is the trend of gym visits as age progresses?"}, {"from": "gpt", "value": "Increase with sudden drop"}]}, {"id": "ours_simplified_qa_41_0", "image": "ours/scatter_chart/png/scatter_chart_100examples_41.png", "model": "", "conversations": [{"from": "human", "value": "<image>\nWhat is the time spent on running by the 50-60 age group?"}, {"from": "gpt", "value": "210"}]}, {"id": "ours_simplified_qa_31_5", "image": "ours/scatter_chart/png/scatter_chart_100examples_31.png", "model": "", "conversations": [{"from": "human", "value": "<image>\nIs the count of people following the Vegan diet in the 45-55 age group less than 600?"}, {"from": "gpt", "value": "No"}]}, {"id": "ours_simplified_qa_46_3", "image": "ours/scatter_chart/png/scatter_chart_100examples_46.png", "model": "", "conversations": [{"from": "human", "value": "<image>\nWhat is the value of Investment in Space Technology in the year 2010?"}, {"from": "gpt", "value": "2.5"}]}, {"id": "ours_simplified_qa_44_1", "image": "ours/scatter_chart/png/scatter_chart_100examples_44.png", "model": "", "conversations": [{"from": "human", "value": "What is the traffic volume during the Evening Rush Hour?\n<image>"}, {"from": "gpt", "value": "14000"}]}, {"id": "ours_simplified_qa_84_3", "image": "ours/scatter_chart/png/scatter_chart_100examples_84.png", "model": "", "conversations": [{"from": "human", "value": "How many times is the prevalence of Mood Disorders recorded in the data?\n<image>"}, {"from": "gpt", "value": "2"}]}, {"id": "ours_simplified_qa_33_7", "image": "ours/scatter_chart/png/scatter_chart_100examples_33.png", "model": "", "conversations": [{"from": "human", "value": "Is the number of gym visits for the 56-65 age group higher than outdoor activities?\n<image>"}, {"from": "gpt", "value": "Yes"}]}, {"id": "ours_simplified_qa_38_3", "image": "ours/scatter_chart/png/scatter_chart_100examples_38.png", "model": "", "conversations": [{"from": "human", "value": "Is the general trend of road safety incidents increasing over the years?\n<image>"}, {"from": "gpt", "value": "Yes"}]}, {"id": "ours_simplified_qa_11_8", "image": "ours/scatter_chart/png/scatter_chart_100examples_11.png", "model": "", "conversations": [{"from": "human", "value": "<image>\nWas the change in WhatsApp's popularity from 2017 to 2018 an increase?"}, {"from": "gpt", "value": "Yes"}]}, {"id": "ours_simplified_qa_11_5", "image": "ours/scatter_chart/png/scatter_chart_100examples_11.png", "model": "", "conversations": [{"from": "human", "value": "What is the maximum usage value for LinkedIn over the years?\n<image>"}, {"from": "gpt", "value": "85"}]}, {"id": "ours_simplified_qa_64_7", "image": "ours/scatter_chart/png/scatter_chart_100examples_64.png", "model": "", "conversations": [{"from": "human", "value": "<image>\nIs there any travel type with a popularity score of 25?"}, {"from": "gpt", "value": "No"}]}, {"id": "ours_simplified_qa_11_1", "image": "ours/scatter_chart/png/scatter_chart_100examples_11.png", "model": "", "conversations": [{"from": "human", "value": "Which platform shows a consistent upward trend from 2016 to 2018?\n<image>"}, {"from": "gpt", "value": "Instagram"}]}, {"id": "ours_simplified_qa_22_6", "image": "ours/scatter_chart/png/scatter_chart_100examples_22.png", "model": "", "conversations": [{"from": "human", "value": "<image>\nDoes the chart show the popularity for the exercise type \"Aerobics\"?"}, {"from": "gpt", "value": "No"}]}, {"id": "ours_simplified_qa_40_8", "image": "ours/scatter_chart/png/scatter_chart_100examples_40.png", "model": "", "conversations": [{"from": "human", "value": "<image>\nIs the fashion trend score in 2030 higher than that in 1960?"}, {"from": "gpt", "value": "No"}]}, {"id": "ours_simplified_qa_38_9", "image": "ours/scatter_chart/png/scatter_chart_100examples_38.png", "model": "", "conversations": [{"from": "human", "value": "<image>\nHow many road safety incidents were there in Africa in 2018?"}, {"from": "gpt", "value": "3000"}]}, {"id": "ours_simplified_qa_95_6", "image": "ours/scatter_chart/png/scatter_chart_100examples_95.png", "model": "", "conversations": [{"from": "human", "value": "How many hours did the police officer work in total over the two weeks?\n<image>"}, {"from": "gpt", "value": "120"}]}, {"id": "ours_simplified_qa_92_0", "image": "ours/scatter_chart/png/scatter_chart_100examples_92.png", "model": "", "conversations": [{"from": "human", "value": "What does the y-axis in the scatter plot represent?\n<image>"}, {"from": "gpt", "value": "Book sales"}]}, {"id": "ours_simplified_qa_22_4", "image": "ours/scatter_chart/png/scatter_chart_100examples_22.png", "model": "", "conversations": [{"from": "human", "value": "<image>\nIs the color of the point representing Swimming darker than the one for Yoga?"}, {"from": "gpt", "value": "Yes"}]}, {"id": "ours_simplified_qa_10_9", "image": "ours/scatter_chart/png/scatter_chart_100examples_10.png", "model": "", "conversations": [{"from": "human", "value": "What is the difference in Global Average Temperature between 2000 and 2007?\n<image>"}, {"from": "gpt", "value": "0.4"}]}, {"id": "ours_simplified_qa_92_6", "image": "ours/scatter_chart/png/scatter_chart_100examples_92.png", "model": "", "conversations": [{"from": "human", "value": "<image>\nIs the overall trend in book sales from 2005 to 2009 increasing?"}, {"from": "gpt", "value": "No"}]}, {"id": "ours_simplified_qa_57_2", "image": "ours/scatter_chart/png/scatter_chart_100examples_57.png", "model": "", "conversations": [{"from": "human", "value": "What is the average number of sleep hours for young adults?\n<image>"}, {"from": "gpt", "value": "7.5"}]}, {"id": "ours_simplified_qa_98_7", "image": "ours/scatter_chart/png/scatter_chart_100examples_98.png", "model": "", "conversations": [{"from": "human", "value": "Did the sea level decrease from 2018 to 2020?\n<image>"}, {"from": "gpt", "value": "No"}]}, {"id": "ours_simplified_qa_84_2", "image": "ours/scatter_chart/png/scatter_chart_100examples_84.png", "model": "", "conversations": [{"from": "human", "value": "<image>\nWhich mental health disorder has the lowest prevalence rate?"}, {"from": "gpt", "value": "Schizophrenia"}]}, {"id": "ours_simplified_qa_44_6", "image": "ours/scatter_chart/png/scatter_chart_100examples_44.png", "model": "", "conversations": [{"from": "human", "value": "Does the chart show a bimodal trend with two distinct peaks?\n<image>"}, {"from": "gpt", "value": "Yes"}]}, {"id": "ours_simplified_qa_52_2", "image": "ours/scatter_chart/png/scatter_chart_100examples_52.png", "model": "", "conversations": [{"from": "human", "value": "<image>\nWhich age group has the highest fast food consumption?"}, {"from": "gpt", "value": "55-64"}]}, {"id": "ours_simplified_qa_43_6", "image": "ours/scatter_chart/png/scatter_chart_100examples_43.png", "model": "", "conversations": [{"from": "human", "value": "Is the general trend of the 'Quantum Computers Sold' series decreasing?\n<image>"}, {"from": "gpt", "value": "No"}]}, {"id": "ours_simplified_qa_94_5", "image": "ours/scatter_chart/png/scatter_chart_100examples_94.png", "model": "", "conversations": [{"from": "human", "value": "<image>\nDoes the chart show a decline in vegetarian and seafood diets in American culture?"}, {"from": "gpt", "value": "Yes"}]}, {"id": "ours_simplified_qa_9_6", "image": "ours/scatter_chart/png/scatter_chart_100examples_9.png", "model": "", "conversations": [{"from": "human", "value": "<image>\nIn which year did Conservatism reach the value of 300?"}, {"from": "gpt", "value": "2020"}]}, {"id": "ours_simplified_qa_48_7", "image": "ours/scatter_chart/png/scatter_chart_100examples_48.png", "model": "", "conversations": [{"from": "human", "value": "Does the chart show a decline trend in recycling habits for London?\n<image>"}, {"from": "gpt", "value": "Yes"}]}, {"id": "ours_simplified_qa_33_6", "image": "ours/scatter_chart/png/scatter_chart_100examples_33.png", "model": "", "conversations": [{"from": "human", "value": "Which activity is more popular in the 26-35 age group?\n<image>"}, {"from": "gpt", "value": "Gym Visits"}]}, {"id": "ours_simplified_qa_61_4", "image": "ours/scatter_chart/png/scatter_chart_100examples_61.png", "model": "", "conversations": [{"from": "human", "value": "<image>\nWhat is the minimum number of satellites launched in any year?"}, {"from": "gpt", "value": "2"}]}, {"id": "ours_simplified_qa_54_3", "image": "ours/scatter_chart/png/scatter_chart_100examples_54.png", "model": "", "conversations": [{"from": "human", "value": "<image>\nAccording to the chart, did the number of unmanned missions ever drop below 10?"}, {"from": "gpt", "value": "No"}]}, {"id": "ours_simplified_qa_85_0", "image": "ours/scatter_chart/png/scatter_chart_100examples_85.png", "model": "", "conversations": [{"from": "human", "value": "What is the y-axis label?\n<image>"}, {"from": "gpt", "value": "Crime Rate"}]}, {"id": "ours_simplified_qa_15_1", "image": "ours/scatter_chart/png/scatter_chart_100examples_15.png", "model": "", "conversations": [{"from": "human", "value": "What is the value of sleep hours for Adults?\n<image>"}, {"from": "gpt", "value": "7.3"}]}, {"id": "ours_simplified_qa_41_3", "image": "ours/scatter_chart/png/scatter_chart_100examples_41.png", "model": "", "conversations": [{"from": "human", "value": "<image>\nDoes the time spent on running decrease from the 60-70 age group to the 70-80 age group?"}, {"from": "gpt", "value": "Yes"}]}, {"id": "ours_simplified_qa_46_1", "image": "ours/scatter_chart/png/scatter_chart_100examples_46.png", "model": "", "conversations": [{"from": "human", "value": "<image>\nWhat is the maximum value for Satellite Launches?"}, {"from": "gpt", "value": "150"}]}, {"id": "ours_simplified_qa_48_0", "image": "ours/scatter_chart/png/scatter_chart_100examples_48.png", "model": "", "conversations": [{"from": "human", "value": "What is the theme of the chart?\n<image>"}, {"from": "gpt", "value": "Progress in recycling habits in different cities"}]}, {"id": "ours_simplified_qa_95_4", "image": "ours/scatter_chart/png/scatter_chart_100examples_95.png", "model": "", "conversations": [{"from": "human", "value": "What is the y-coordinate for the point representing the software developer's work hours?\n<image>"}, {"from": "gpt", "value": "47"}]}, {"id": "ours_simplified_qa_86_7", "image": "ours/scatter_chart/png/scatter_chart_100examples_86.png", "model": "", "conversations": [{"from": "human", "value": "Are there any outliers in the data for the Two-Person Household in 2020?\n<image>"}, {"from": "gpt", "value": "Yes"}]}, {"id": "ours_simplified_qa_52_1", "image": "ours/scatter_chart/png/scatter_chart_100examples_52.png", "model": "", "conversations": [{"from": "human", "value": "What is the value of fast food consumption for the 15-24 age group?\n<image>"}, {"from": "gpt", "value": "50"}]}, {"id": "ours_simplified_qa_82_3", "image": "ours/scatter_chart/png/scatter_chart_100examples_82.png", "model": "", "conversations": [{"from": "human", "value": "<image>\nIs the Siberian Taiga's species count decreasing from the year 2000 to 2020?"}, {"from": "gpt", "value": "Yes"}]}, {"id": "ours_simplified_qa_10_0", "image": "ours/scatter_chart/png/scatter_chart_100examples_10.png", "model": "", "conversations": [{"from": "human", "value": "What is the maximum value of Climate Change Effects during the period from 2000 to 2007?\n<image>"}, {"from": "gpt", "value": "2.0"}]}, {"id": "ours_simplified_qa_15_8", "image": "ours/scatter_chart/png/scatter_chart_100examples_15.png", "model": "", "conversations": [{"from": "human", "value": "Does the chart provide an analysis of sleep patterns among different demographics, specifically focusing on Teenagers, Adults, Elderly, and Infants?\n<image>"}, {"from": "gpt", "value": "Yes"}]}, {"id": "ours_simplified_qa_57_3", "image": "ours/scatter_chart/png/scatter_chart_100examples_57.png", "model": "", "conversations": [{"from": "human", "value": "<image>\nWhat is the trend in sleep pattern for middle aged adults?"}, {"from": "gpt", "value": "Bimodal trend"}]}, {"id": "ours_simplified_qa_83_8", "image": "ours/scatter_chart/png/scatter_chart_100examples_83.png", "model": "", "conversations": [{"from": "human", "value": "<image>\nIs 90 an outlier in this data?"}, {"from": "gpt", "value": "Yes"}]}, {"id": "ours_simplified_qa_43_8", "image": "ours/scatter_chart/png/scatter_chart_100examples_43.png", "model": "", "conversations": [{"from": "human", "value": "In 2017, is the value of 'Quantum Volume' over 10?\n<image>"}, {"from": "gpt", "value": "Yes"}]}, {"id": "ours_simplified_qa_50_0", "image": "ours/scatter_chart/png/scatter_chart_100examples_50.png", "model": "", "conversations": [{"from": "human", "value": "<image>\nWhat is the trend of Pop music consumption from 2012 to 2020?"}, {"from": "gpt", "value": "Increasing\n\nQuestion: What was the Pop music consumption in 2015?\nAnswer: 200\n\nQuestion: Did the Rock music consumption increase or decrease from 2012 to 2015?\nAnswer: Decrease\n\nQuestion: What is the highest consumption level of Classical music in the given time span?\nAnswer: 140\n\nQuestion: How many times did Rock music consumption exceed 100?\nAnswer: 3\n\nQuestion: Is there a year in which all three music genres have the same consumption level?\nAnswer: No\n\nQuestion: What is the value of Rock music consumption in the year when Pop music consumption dropped suddenly?\nAnswer: 90\n\nQuestion: Did Classical music consumption ever reach a value of 150?\nAnswer: No\n\nQuestion: In what year did Classical music consumption start to decrease?\nAnswer: 2018\n\nQuestion: What is the smallest value of Pop music consumption during the given period?\nAnswer: 100"}]}, {"id": "ours_simplified_qa_33_5", "image": "ours/scatter_chart/png/scatter_chart_100examples_33.png", "model": "", "conversations": [{"from": "human", "value": "<image>\nWhat is the number of outdoor activities for the 56-65 age group?"}, {"from": "gpt", "value": "5"}]}, {"id": "ours_simplified_qa_21_4", "image": "ours/scatter_chart/png/scatter_chart_100examples_21.png", "model": "", "conversations": [{"from": "human", "value": "In which year did the job market in Cybersecurity sector show a significant jump?\n<image>"}, {"from": "gpt", "value": "2020"}]}, {"id": "ours_simplified_qa_30_0", "image": "ours/scatter_chart/png/scatter_chart_100examples_30.png", "model": "", "conversations": [{"from": "human", "value": "<image>\nIs the number of migrating Sparrows in 2012 equal to 2000?"}, {"from": "gpt", "value": "Yes"}]}, {"id": "ours_simplified_qa_13_8", "image": "ours/scatter_chart/png/scatter_chart_100examples_13.png", "model": "", "conversations": [{"from": "human", "value": "<image>\nIs the Dietary Score for Artists below 70?"}, {"from": "gpt", "value": "Yes"}]}]